deadend_cli/__init__.py
deadend_cli/banner.py
deadend_cli/chat.py
deadend_cli/cli.py
deadend_cli/component_manager.py
deadend_cli/console.py
deadend_cli/eval.py
deadend_cli/event_bus.py
deadend_cli/hooks_adapter.py
deadend_cli/init.py
deadend_cli/main.py
deadend_cli/rpc_models.py
deadend_cli/rpc_server.py
deadend_cli/data/vendor_specific_files.json
deadend_cli/data/memory/reusable_credentials.json
deadend_agent/__init__.py
deadend_agent/core.py
deadend_agent/deadend_agent.py
deadend_agent/exceptions.py
deadend_agent/hooks.py
deadend_agent/agents/__init__.py
deadend_agent/agents/architecture.py
deadend_agent/agents/exploit_web_agent.py
deadend_agent/agents/factory.py
deadend_agent/agents/judge.py
deadend_agent/agents/planner.py
deadend_agent/agents/recon_threatmodel_agent.py
deadend_agent/agents/reporter.py
deadend_agent/agents/supervisor_agent.py
deadend_agent/agents/validator.py
deadend_agent/agents/components/__init__.py
deadend_agent/agents/components/executor.py
deadend_agent/agents/components/planner.py
deadend_agent/agents/components/validator.py
deadend_agent/agents/generic_agents/__init__.py
deadend_agent/agents/generic_agents/python_interpreter_agent.py
deadend_agent/agents/generic_agents/request_agent.py
deadend_agent/agents/generic_agents/shell_agent.py
deadend_agent/code_indexer/__init__.py
deadend_agent/code_indexer/code_splitter.py
deadend_agent/code_indexer/language_patterns.py
deadend_agent/config/__init__.py
deadend_agent/config/settings.py
deadend_agent/context/__init__.py
deadend_agent/context/context_engine.py
deadend_agent/context/memory.py
deadend_agent/core_agent/__init__.py
deadend_agent/core_agent/core_agent.py
deadend_agent/core_agent/session_metrics.py
deadend_agent/core_agent/telemetry.py
deadend_agent/data/vendor_specific_files.json
deadend_agent/data/memory/reusable_credentials.json
deadend_agent/embedders/__init__.py
deadend_agent/embedders/code_indexer.py
deadend_agent/embedders/embedders.py
deadend_cli-0.0.15.dist-info/METADATA
deadend_cli-0.0.15.dist-info/WHEEL
deadend_cli-0.0.15.dist-info/entry_points.txt
deadend_cli-0.0.15.dist-info/RECORD
