Metadata-Version: 2.4
Name: deadend_cli
Version: 0.0.15
Summary: AI agent CLI for security research
Author-email: Yassine Bargach <yassine.bargach@proton.me>
Requires-Python: >=3.11
Requires-Dist: aiofiles>=24.1.0
Requires-Dist: aiohttp>=3.12.14
Requires-Dist: asgiref>=3.8.1
Requires-Dist: asyncpg>=0.30.0
Requires-Dist: beautifulsoup4>=4.13.4
Requires-Dist: cssbeautifier>=1.15.4
Requires-Dist: deadend-agent
Requires-Dist: deadend-eval
Requires-Dist: deadend-prompts
Requires-Dist: docker>=7.1.0
Requires-Dist: dotenv>=0.9.9
Requires-Dist: google-genai>=1.18.0
Requires-Dist: httptools>=0.6.4
Requires-Dist: jinja2>=3.1.6
Requires-Dist: jsbeautifier>=1.15.4
Requires-Dist: logfire>=4.3.3
Requires-Dist: logging>=0.4.9.6
Requires-Dist: lxml>=6.0.0
Requires-Dist: nest-asyncio>=1.6.0
Requires-Dist: numpy>=2.3.1
Requires-Dist: pgvector>=0.4.1
Requires-Dist: playwright>=1.56.0
Requires-Dist: prompt-toolkit>=3.0.51
Requires-Dist: pydantic-ai-slim[google,openai,openrouter]>=1.9.1
Requires-Dist: pydantic-ai>=1.9.1
Requires-Dist: pydantic>=2.11.5
Requires-Dist: python-frontmatter>=1.1.0
Requires-Dist: pyyaml>=6.0.2
Requires-Dist: readchar>=4.2.1
Requires-Dist: rich>=14.0.0
Requires-Dist: semantic-text-splitter>=0.27.0
Requires-Dist: sqlalchemy>=2.0.41
Requires-Dist: tenacity>=9.1.2
Requires-Dist: tiktoken>=0.9.0
Requires-Dist: toml>=0.10.2
Requires-Dist: tree-sitter-css>=0.23.2
Requires-Dist: tree-sitter-html>=0.23.2
Requires-Dist: tree-sitter-javascript>=0.23.1
Requires-Dist: tree-sitter-markdown>=0.5.1
Requires-Dist: tree-sitter-typescript>=0.23.2
Requires-Dist: typer>=0.15.4
Requires-Dist: typing-extensions>=4.15.0
Requires-Dist: zaproxy>=0.4.0
